real_wordpiece/__init__.py
real_wordpiece/trainer.py
real_wordpiece-0.1.7.dist-info/LICENSE
real_wordpiece-0.1.7.dist-info/METADATA
real_wordpiece-0.1.7.dist-info/WHEEL
real_wordpiece-0.1.7.dist-info/RECORD
